README.md
setup.cfg
setup.py
localize_py/Translator.py
localize_py/__init__.py
localize_py.egg-info/PKG-INFO
localize_py.egg-info/SOURCES.txt
localize_py.egg-info/dependency_links.txt
localize_py.egg-info/not-zip-safe
localize_py.egg-info/top_level.txt