Metadata-Version: 2.1
Name: localize-py
Version: 0.8.1.5
Summary: Localization simplified.
Home-page: https://github.com/Alex-Blade/localize-py
Author-email: alexlaki1@yandex.ru
License: UNKNOWN
Platform: UNKNOWN
Classifier: Programming Language :: Python :: 3
Classifier: License :: OSI Approved :: MIT License
Classifier: Operating System :: OS Independent
Requires-Python: >=3.6
